pihole_exporter/__init__.py
pihole_exporter/pihole_exporter.py
pihole_exporter-0.4.6.7.dist-info/LICENSE
pihole_exporter-0.4.6.7.dist-info/METADATA
pihole_exporter-0.4.6.7.dist-info/WHEEL
pihole_exporter-0.4.6.7.dist-info/entry_points.txt
pihole_exporter-0.4.6.7.dist-info/top_level.txt
pihole_exporter-0.4.6.7.dist-info/RECORD
