Metadata-Version: 2.1
Name: pihole-exporter
Version: 0.4.6.7
Summary: Export pihole metrics for prometheus
Home-page: https://github.com/dr1s/pihole_exporter.py
Author: dr1s
Author-email: dr1s@drs.li
License: MIT
Platform: UNKNOWN
Requires-Dist: prometheus-metrics (>=0.1.6.5)
